tspoon/__init__.py
tspoon/main.py
tspoon-0.2.11.dist-info/METADATA
tspoon-0.2.11.dist-info/WHEEL
tspoon-0.2.11.dist-info/top_level.txt
tspoon-0.2.11.dist-info/RECORD
