Metadata-Version: 2.1
Name: tspoon
Version: 0.2.11
Summary: Time-series pre-processing, period conversion, normalization, visualization, and more.
